Workbook

Sheet README
A1: Purpose
A2: This model evaluates customer segment profitability, cost-to-serve, and operating model tradeoffs to inform a 12–24 month business transformation strategy.
A3: Key Questions
A4: • Which customer segments drive profit vs. cost?
A5: • Where is cost-to-serve misaligned with value?
A6: • What transformation levers have the highest impact?
A7: How to Use
A8: • Adjust assumptions in the Assumptions tab
A9: • Review segment economics and margins
A10: • Compare scenarios to evaluate tradeoffs
A11: Important Notes
A12: • Data is representative and directional
A13: • Model designed for decision support, not accounting precision

Sheet Assumptions
A1: assumption | B1: value
A2: Support Automation Rate | B2: 0.2
A3: Support Cost Reduction | B3: 0.15
A4: Pro Segment Price Increase | B4: 0.08
A5: SMB Growth Increase | B5: 0.05
A6: Enterprise Churn Reduction | B6: 0.01

Sheet Customer_Economics
A1: Segment | B1: Users | C1: ARPU (annual) | D1: Revenue | E1: Support Cost per User | F1: Total Support Cost | G1: Gross Contribution
A2: Retail | B2: 2400000 | C2: 85 | D2: =B2*C2 -> 204000000 | E2: 42 | F2: =B2*E2 -> 100800000 | G2: =D2-F2 -> 103200000
A3: Pro | B3: 520000 | C3: 310 | D3: =B3*C3 -> 161200000 | E3: 68 | F3: =B3*E3 -> 35360000 | G3: =D3-F3 -> 125840000
A4: SMB | B4: 230000 | C4: 1250 | D4: =B4*C4 -> 287500000 | E4: 210 | F4: =B4*E4 -> 48300000 | G4: =D4-F4 -> 239200000
A5: Enterprise | B5: 50000 | C5: 7800 | D5: =B5*C5 -> 390000000 | E5: 950 | F5: =B5*E5 -> 47500000 | G5: =D5-F5 -> 342500000

Sheet Cost_Structure
A1: Function | B1: Headcount | C1: Avg_Cost_Per_Employee | D1: Total_Cost | E1: Percent_of_Total
A2: Customer Support | B2: 620 | C2: 72000 | D2: =B2*C2 -> 44640000 | E2: =D2/$D$7 -> 0.23458931
A3: Operations | B3: 310 | C3: 95000 | D3: =B3*C3 -> 29450000 | E3: =D3/$D$7 -> 0.15476378
A4: Engineering | B4: 480 | C4: 145000 | D4: =B4*C4 -> 69600000 | E4: =D4/$D$7 -> 0.36575753
A5: Compliance & Risk | B5: 140 | C5: 110000 | D5: =B5*C5 -> 15400000 | E5: =D5/$D$7 -> 0.080929108
A6: Sales & Marketing | B6: 260 | C6: 120000 | D6: =B6*C6 -> 31200000 | E6: =D6/$D$7 -> 0.16396027
D7: =SUM(D2:D6) -> 190290000 | E7: =SUM(E2:E6) -> 1

Sheet Segment_Margins
A1: Segment | B1: Revenue | C1: Support_Cost | D1: Allocated_Support_Cost | E1: Contribution_After_Support | F1: Contribution_Margin
A2: =Customer_Economics!A2 -> Retail | B2: =Customer_Economics!D2 -> 204000000 | C2: =Customer_Economics!F2 -> 100800000 | D2: =C2 -> 100800000 | E2: =B2-D2 -> 103200000 | F2: =E2/B2 -> 0.50588235
A3: =Customer_Economics!A3 -> Pro | B3: =Customer_Economics!D3 -> 161200000 | C3: =Customer_Economics!F3 -> 35360000 | D3: =C3 -> 35360000 | E3: =B3-D3 -> 125840000 | F3: =E3/B3 -> 0.78064516
A4: =Customer_Economics!A4 -> SMB | B4: =Customer_Economics!D4 -> 287500000 | C4: =Customer_Economics!F4 -> 48300000 | D4: =C4 -> 48300000 | E4: =B4-D4 -> 239200000 | F4: =E4/B4 -> 0.832
A5: =Customer_Economics!A5 -> Enterprise | B5: =Customer_Economics!D5 -> 390000000 | C5: =Customer_Economics!F5 -> 47500000 | D5: =C5 -> 47500000 | E5: =B5-D5 -> 342500000 | F5: =E5/B5 -> 0.87820513

Sheet Scenarios
A1: Scenario | B1: Total_Revenue | C1: Total_Support_Cost | D1: Contribution_After_Support | E1: Contribution_Margin | F1: Key_Assumption
A2: Base Case | B2: =SUM(Segment_Margins!B2:B5) -> 1042700000 | C2: =SUM(Segment_Margins!D2:D5) -> 231960000 | D2: =B2-C2 -> 810740000 | E2: =D2/B2 -> 0.77753908 | F2: No operational changes
A3: Targeted Automation | B3: =B2 -> 1042700000 | C3: =C2*(1-Assumptions!B2) -> 185568000 | D3: =B3-C3 -> 857132000 | E3: =D3/B3 -> 0.82203126 | F3: 20% reduction in support cost via automation
A4: Segment-Focused Operating Model | B4: =B2*(1+0.03) -> 1073981000 | C4: =C2*(1-0.3) -> 162372000 | D4: =B4-C4 -> 911609000 | E4: =D4/B4 -> 0.84881297 | F4: Support effort reallocated toward high-value segments

Sheet Executive_Summary
A1: Executive Summary — Business Transformation Impact
A3: This summary compares baseline performance against two transformation scenarios to assess impact on profitability and operating efficiency.
A6: Metric | B6: Base Case | C6: Targeted Automation | D6: Segment-Focused Model
A7: Total Revenue | B7: =Scenarios!B2 -> 1042700000 | C7: =Scenarios!B3 -> 1042700000 | D7: =Scenarios!B4 -> 1073981000
A8: Total Support Cost | B8: =Scenarios!C2 -> 231960000 | C8: =Scenarios!C3 -> 185568000 | D8: =Scenarios!C4 -> 162372000
A9: Contribution After Support | B9: =Scenarios!D2 -> 810740000 | C9: =Scenarios!D3 -> 857132000 | D9: =Scenarios!D4 -> 911609000
A10: Contribution Margin | B10: =Scenarios!E2 -> 0.77753908 | C10: =Scenarios!E3 -> 0.82203126 | D10: =Scenarios!E4 -> 0.84881297
A13: Metric | B13: Δ Automation vs Base | C13: Δ Segment-Focused vs Base
A14: Contribution After Support | B14: =Scenarios!D3-Scenarios!D2 -> 46392000 | C14: =Scenarios!D4-Scenarios!D2 -> 100869000
A15: Contribution Margin | B15: =Scenarios!E3-Scenarios!E2 -> 0.044492184 | C15: =Scenarios!E4-Scenarios!E2 -> 0.071273887
A17: • Targeted automation improves margins but does not materially change revenue trajectory
A18: • Segment-focused operating model delivers the largest improvement in contribution and margin
A19: • Cost-to-serve misalignment is a primary driver of underperformance
A20: • Transformation impact is driven by focus, not scale
